README.rst
setup.py
bin/pfdicomtag
pfdicomtag/__init__.py
pfdicomtag/pfdicomtag.py
pfdicomtag.egg-info/PKG-INFO
pfdicomtag.egg-info/SOURCES.txt
pfdicomtag.egg-info/dependency_links.txt
pfdicomtag.egg-info/not-zip-safe
pfdicomtag.egg-info/requires.txt
pfdicomtag.egg-info/top_level.txt