Metadata-Version: 1.0
Name: pfdicomtag
Version: 1.0.0
Summary: (Python) utility to extract meta data from trees of organized DICOM files.
Home-page: https://github.com/FNNDSC/med2image
Author: FNNDSC
Author-email: dev@babymri.org
License: MIT
Platform: UNKNOWN
